epintervene/__init__.py
epintervene/simobjects/__init__.py
epintervene/simobjects/eventtype.py
epintervene/simobjects/extended_simulation.py
epintervene/simobjects/network.py
epintervene/simobjects/nodestate.py
epintervene/simobjects/simulation.py
examples/__init__.py
examples/interventions_sandbox.py
examples/sandbox.py
tests/__init__.py
tests/test_simobjects/__init__.py
tests/test_simobjects/test_extended_simulation.py
tests/test_simobjects/test_network.py
tests/test_simobjects/test_simulation.py
epintervene-1.1.1.dist-info/LICENSE.txt
epintervene-1.1.1.dist-info/METADATA
epintervene-1.1.1.dist-info/WHEEL
epintervene-1.1.1.dist-info/top_level.txt
epintervene-1.1.1.dist-info/RECORD
