Metadata-Version: 2.1
Name: epintervene
Version: 1.1.1
Summary: EpIntervene Simulation Package
Home-page: https://github.com/andrea-allen/epintervene
Author: Andrea Allen
Author-email: andrea2allen@gmail.com
Project-URL: Bug Tracker, https://github.com/andrea-allen/epintervene/issues
Project-URL: Documentation, https://github.com/andrea-allen/epintervene
Keywords: python,epintervene
Classifier: Development Status :: 1 - Planning
Classifier: Intended Audience :: Science/Research
Classifier: Programming Language :: Python :: 2
Classifier: Programming Language :: Python :: 3
Classifier: Operating System :: MacOS :: MacOS X
Classifier: Operating System :: Microsoft :: Windows
Requires-Python: >=3.6
License-File: LICENSE.txt
